CHANGES
MANIFEST.in
README
setup.cfg
setup.py
epubmaker/CSSApplicator.py
epubmaker/CommonOptions.py
epubmaker/EpubMaker.py
epubmaker/HTMLChunker.py
epubmaker/ParserFactory.py
epubmaker/Spider.py
epubmaker/Unitame.py
epubmaker/UnitameData.py
epubmaker/Version.py
epubmaker/WriterFactory.py
epubmaker/__init__.py
epubmaker.egg-info/PKG-INFO
epubmaker.egg-info/SOURCES.txt
epubmaker.egg-info/dependency_links.txt
epubmaker.egg-info/entry_points.txt
epubmaker.egg-info/requires.txt
epubmaker.egg-info/top_level.txt
epubmaker.egg-info/zip-safe
epubmaker/lib/DublinCore.py
epubmaker/lib/GutenbergGlobals.py
epubmaker/lib/Logger.py
epubmaker/lib/MediaTypes.py
epubmaker/lib/__init__.py
epubmaker/mydocutils/__init__.py
epubmaker/mydocutils/nodes.py
epubmaker/mydocutils/parsers/GutenbergRSTParser.py
epubmaker/mydocutils/parsers/__init__.py
epubmaker/mydocutils/transforms/__init__.py
epubmaker/mydocutils/transforms/parts.py
epubmaker/mydocutils/writers/GutenbergHTMLWriter.py
epubmaker/mydocutils/writers/GutenbergKindlegenWriter.py
epubmaker/mydocutils/writers/GutenbergNroffWriter.py
epubmaker/mydocutils/writers/NroffWriter.py
epubmaker/mydocutils/writers/XetexWriter.py
epubmaker/mydocutils/writers/__init__.py
epubmaker/packagers/HTMLPackager.py
epubmaker/packagers/PDFPackager.py
epubmaker/packagers/PushPackager.py
epubmaker/packagers/RSTPackager.py
epubmaker/packagers/TxtPackager.py
epubmaker/packagers/__init__.py
epubmaker/parsers/AuxParser.py
epubmaker/parsers/CSSParser.py
epubmaker/parsers/HTMLParser.py
epubmaker/parsers/ImageParser.py
epubmaker/parsers/RSTParser.py
epubmaker/parsers/__init__.py
epubmaker/parsers/broken.png
epubmaker/parsers/pg-license.rst
epubmaker/writers/EpubWriter.py
epubmaker/writers/HTMLWriter.py
epubmaker/writers/KindleWriter.py
epubmaker/writers/PDFWriter.py
epubmaker/writers/RSTWriter.py
epubmaker/writers/TxtWriter.py
epubmaker/writers/__init__.py
epubmaker/writers/cover.jpg
epubmaker/writers/rst2all.css
epubmaker/writers/rst2epub.css
epubmaker/writers/rst2html.css
epubmaker/writers/rst2kindle.css