Metadata-Version: 1.1
Name: epubmaker
Version: 0.3.17
Summary: The Project Gutenberg Epub Maker
Home-page: http://pypi.python.org/pypi/epubmaker/
Author: Marcello Perathoner
Author-email: webmaster@gutenberg.org
License: GPL v3
Keywords: epub rst reST reStructuredText gutenberg ebook conversion
Platform: OS-independent
Classifier: Topic :: Text Processing
Classifier: License :: OSI Approved :: GNU General Public License (GPL)
Classifier: Environment :: Console
Classifier: Operating System :: OS Independent
Classifier: Intended Audience :: Other Audience
Classifier: Development Status :: 4 - Beta
Requires: setuptools
Requires: docutils (>= 0.7)
Requires: lxml (>= 2.2.8)
Requires: cssutils (>= 0.9.8a1)
Requires: PIL (>= 1.1.7)
